{"artwork":null,"bars":20,"bpm":120,"collaborative":false,"color":"#5bc6fc","created":"2025-09-09 01:44:36.946000","deleted":false,"description":"","gadget-details":[{"beats":36,"color":"#2f9aef","created":"2025-10-07 00:33:17.756000","deleted":false,"description":"","id":859097,"idata":{"author":"Anonymous","cloned":false,"displayOrder":2,"editor-theme":"tunepad-dark","gain":1.64285502433838,"hasError":false,"midi-input":false,"midi-output":false,"minimized":false,"pan":0.0029687500000004086,"patchId":11,"python":"playNote(1, beats = 0.25)\nrest(0.50)\nplayNote(1, beats = 0.25)\nrest(0.50)\nplayNote(1, beats = 0.25)\nrest(0.50)\nplayNote(1, beats = 0.25)\nrest(0.50)\nplayNote(1, beats = 0.25)\nrest(0.50)\nplayNote(1, beats = 0.25)\nrest(0.50)\nplayNote(1, beats = 0.25)\nrest(0.50)\nplayNote(1, beats = 0.25)\nrest(0.50)\nplayNote(1, beats = 0.25)\nrest(0.50)\nplayNote(1, beats = 0.25)\nrest(0.50)\nplayNote(1, beats = 0.25)\nrest(0.50)\nplayNote(1, beats = 0.25)\nrest(0.50)\nplayNote(1, beats = 0.25)\nrest(0.50)\nplayNote(1, beats = 0.25)\nrest(0.50)\nplayNote(1, beats = 0.25)\nrest(0.50)\nplayNote(1, beats = 0.25)\nrest(0.50)\nplayNote(1, beats = 0.25)\nrest(0.50)\nplayNote(1, beats = 0.25)\nrest(0.50)\nplayNote(1, beats = 0.25)\nrest(0.50)\nplayNote(1, beats = 0.25)\nrest(0.50)\nplayNote(1, beats = 0.25)\nrest(0.50)\nplayNote(1, beats = 0.25)\nrest(0.50)\nplayNote(1, beats = 0.25)\nrest(0.50)\nplayNote(1, beats = 0.25)\nrest(0.50)\nplayNote(1, beats = 0.25)\nrest(0.50)\nplayNote(1, beats = 0.25)\nrest(0.50)\nplayNote(1, beats = 0.25)\nrest(0.50)\nplayNote(1, beats = 0.25)\nrest(0.50)\nplayNote(1, beats = 0.25)\nrest(0.50)\nplayNote(1, beats = 0.25)\nrest(0.50)\nplayNote(1, beats = 0.25)\nrest(0.50)\nplayNote(1, beats = 0.25)\nrest(0.50)\nplayNote(1, beats = 0.25)\nrest(0.50)\nplayNote(1, beats = 0.25)\nrest(0.50)\nplayNote(1, beats = 0.25)\nrest(0.50)\nplayNote(1, beats = 0.25)\nrest(0.50)\nplayNote(1, beats = 0.25)\nrest(0.50)\nplayNote(1, beats = 0.25)\nrest(0.50)\nplayNote(1, beats = 0.25)\nrest(0.50)\nplayNote(1, beats = 0.25)\nrest(0.50)\nplayNote(1, beats = 0.25)\nrest(0.50)\nplayNote(1, beats = 0.25)\nrest(0.50)\nplayNote(1, beats = 0.25)\nrest(0.50)\nplayNote(1, beats = 0.25)\nrest(0.50)\nplayNote(1, beats = 0.25)\nrest(0.50)\nplayNote(1, beats = 0.25)\nrest(0.50)\nplayNote(1, beats = 0.25)\nrest(0.50)\nplayNote(1, beats = 0.25)\nrest(0.50)","show-editor":true,"show-instrument":true,"show-notation":true,"show-output":false,"show-timeline":true},"instrument":"drums","modified":"2025-11-07 09:55:12.359000","name":"Drum (Kick Drum Line)","public":false,"remix_parent":null,"version":"2.0","voice":"piano"},{"beats":8,"color":"#2f9aef","created":"2025-10-07 00:43:50.432000","deleted":false,"description":"","id":859106,"idata":{"author":"Anonymous","cloned":false,"displayOrder":1,"editor-theme":"tunepad-dark","gain":1.6474276743298042,"hasError":false,"midi-input":false,"midi-output":false,"minimized":false,"pan":0,"patchId":11,"python":"playNote(4, beats = 0.25)\nrest(0.25)\nplayNote(4, beats = 0.25)\nrest(0.25)\nplayNote(5, beats = 0.25)\nrest(0.25)\nplayNote(4, beats = 0.25)\nrest(0.25)\nplayNote(4, beats = 0.25)\nrest(0.25)\nplayNote(4, beats = 0.25)\nrest(0.25)\nplayNote(5, beats = 0.25)\nrest(0.25)\nplayNote(4, beats = 0.25)\nrest(0.25)\nplayNote(4, beats = 0.25)\nrest(0.25)\nplayNote(4, beats = 0.25)\nrest(0.25)\nplayNote(5, beats = 0.25)\nrest(0.25)\nplayNote(4, beats = 0.25)\nrest(0.25)\nplayNote(4, beats = 0.25)\nrest(0.25)\nplayNote(4, beats = 0.25)\nrest(0.25)\nplayNote(5, beats = 0.25)\nrest(0.25)\nplayNote(4, beats = 0.25)\n\n\n\n\n","show-editor":true,"show-instrument":true,"show-notation":true,"show-output":false,"show-timeline":true},"instrument":"drums","modified":"2025-11-07 09:51:49.629000","name":"Hi-Hat","public":false,"remix_parent":null,"version":"2.0","voice":"piano"},{"beats":8,"color":"#2f9aef","created":"2025-10-14 00:37:03.988000","deleted":false,"description":"","id":865963,"idata":{"author":"Anonymous","cloned":false,"displayOrder":3,"editor-theme":"tunepad-dark","gain":1.6735506583477617,"hasError":false,"midi-input":false,"midi-output":false,"minimized":false,"pan":0,"patchId":11,"python":"playNote(2, beats = 0.00, sustain = 0.25)\nplayNote(2, beats = 0.25)\nrest(0.50)\nplayNote(2, beats = 0.00, sustain = 0.25)\nplayNote(2, beats = 0.25)\nrest(0.50)\nplayNote(2, beats = 0.00, sustain = 0.25)\nplayNote(2, beats = 0.25)\nrest(0.75)\nplayNote(2, beats = 0.00, sustain = 0.25)\nplayNote(2, beats = 0.25)\nrest(0.25)\nplayNote(2, beats = 0.00, sustain = 0.25)\nplayNote(2, beats = 0.25)\nrest(0.75)\nplayNote(2, beats = 0.00, sustain = 0.25)\nplayNote(2, beats = 0.25)\nrest(0.50)\nplayNote(2, beats = 0.00, sustain = 0.25)\nplayNote(2, beats = 0.25)\nrest(0.50)\nplayNote(2, beats = 0.00, sustain = 0.25)\nplayNote(2, beats = 0.25)\nrest(0.75)\nplayNote(2, beats = 0.00, sustain = 0.25)\nplayNote(2, beats = 0.25)\nrest(0.25)\nplayNote(2, beats = 0.00, sustain = 0.25)\nplayNote(2, beats = 0.25)","show-editor":true,"show-instrument":true,"show-notation":true,"show-output":false,"show-timeline":true},"instrument":"drums","modified":"2025-11-07 09:52:37.910000","name":"Snare","public":false,"remix_parent":null,"version":"2.0","voice":"piano"},{"beats":16,"color":"#2f9aef","created":"2022-02-17 13:53:38.489000","deleted":false,"description":"","id":875565,"idata":{"author":"Anonymous","cloned":true,"displayOrder":5,"editor-theme":"tunepad-dark","gain":1.0299294601188218,"hasError":false,"midi-input":false,"midi-output":false,"minimized":false,"pan":0,"patchId":9,"python":"playNote([48,52,55],beats=4)\nplayNote([53,57,60],beats=4)\nplayNote([55,59,62],beats=4)\nplayNote([48,52,55],beats=4)\n","show-editor":true,"show-instrument":true,"show-notation":true,"show-output":false,"show-timeline":true},"instrument":"piano","modified":"2025-11-07 09:24:06.091000","name":"Chords","public":false,"remix_parent":null,"version":"2.0","voice":"piano"},{"beats":16,"color":"#2f9aef","created":"2025-11-05 10:58:48.996000","deleted":false,"description":"","id":875567,"idata":{"author":"Anonymous","cloned":false,"displayOrder":7,"editor-theme":"tunepad-dark","gain":0.887124613448303,"hasError":false,"midi-input":false,"midi-output":false,"minimized":false,"pan":0,"patchId":9,"python":"playNote(48, beats = 0.25)\nrest(0.25)\nplayNote(48, beats = 0.50)\nrest(0.50)\nplayNote(48, beats = 0.25)\nrest(0.50)\nplayNote(48, beats = 0.25)\nrest(0.50)\nplayNote(48, beats = 0.50)\nrest(0.50)\nplayNote(53, beats = 0.25)\nrest(0.25)\nplayNote(53, beats = 0.50)\nrest(0.50)\nplayNote(53, beats = 0.25)\nrest(0.50)\nplayNote(53, beats = 0.25)\nrest(0.50)\nplayNote(53, beats = 0.50)\nrest(0.50)\nplayNote(55, beats = 0.25)\nrest(0.25)\nplayNote(55, beats = 0.50)\nrest(0.50)\nplayNote(55, beats = 0.25)\nrest(0.50)\nplayNote(55, beats = 0.25)\nrest(0.50)\nplayNote(55, beats = 0.50)\nrest(0.50)\nplayNote(48, beats = 0.25)\nrest(0.25)\nplayNote(48, beats = 0.50)\nrest(0.50)\nplayNote(48, beats = 0.25)\nrest(0.50)\nplayNote(48, beats = 0.25)\nrest(0.50)\nplayNote(48, beats = 0.50)\nrest(0.50)","show-editor":true,"show-instrument":true,"show-notation":true,"show-output":false,"show-timeline":true},"instrument":"piano","modified":"2025-11-07 09:24:11.955000","name":"Main Line","public":false,"remix_parent":null,"version":"2.0","voice":"piano"},{"beats":16,"color":"#2f9aef","created":"2025-11-05 23:24:21.095000","deleted":false,"description":"","id":875697,"idata":{"author":"Anonymous","cloned":false,"displayOrder":7,"editor-theme":"tunepad-dark","gain":1.1462081089913922,"hasError":false,"midi-input":false,"midi-output":false,"minimized":false,"pan":-0.6709375,"patchId":2,"python":"playNote([48,52,55],beats=4)\nplayNote([53,57,60],beats=4)\nplayNote([55,59,62],beats=4)\nplayNote([48,52,55],beats=4)","show-editor":true,"show-instrument":true,"show-notation":true,"show-output":false,"show-timeline":true},"instrument":"guitar","modified":"2025-11-07 09:24:20.839000","name":"Guitar Code","public":false,"remix_parent":null,"version":"2.0","voice":"piano"},{"beats":16,"color":"#2f9aef","created":"2025-11-05 23:26:37.642000","deleted":false,"description":"","id":875698,"idata":{"author":"Anonymous","cloned":false,"displayOrder":7,"editor-theme":"tunepad-dark","gain":1.0829315307636382,"hasError":false,"midi-input":false,"midi-output":false,"minimized":false,"pan":0.2642187499999995,"patchId":2,"python":"playNote([60,64,67],beats=4)\nplayNote([65,69,72],beats=4)\nplayNote([67,71,74],beats=4)\nplayNote([60,64,67],beats=4)","show-editor":true,"show-instrument":true,"show-notation":true,"show-output":false,"show-timeline":true},"instrument":"guitar","modified":"2025-11-07 09:53:27.893000","name":"High octave chord","public":false,"remix_parent":null,"version":"2.0","voice":"piano"},{"beats":16,"color":"#2f9aef","created":"2025-11-05 23:37:01.246000","deleted":false,"description":"","id":875699,"idata":{"author":"Anonymous","cloned":false,"displayOrder":8,"editor-theme":"tunepad-dark","gain":1.0610575539078482,"hasError":false,"midi-input":false,"midi-output":false,"minimized":false,"pan":0,"patchId":9,"python":"playNote([60,64,67],beats=4)\nplayNote([65,69,72],beats=4)\nplayNote([67,71,74],beats=4)\nplayNote([60,64,67],beats=4)","show-editor":true,"show-instrument":true,"show-notation":true,"show-output":false,"show-timeline":true},"instrument":"piano","modified":"2025-11-07 09:40:05.286000","name":"Key 3 base","public":false,"remix_parent":null,"version":"2.0","voice":"piano"},{"beats":16,"color":"#2f9aef","created":"2025-11-05 23:42:08.257000","deleted":false,"description":"","id":875700,"idata":{"author":"Anonymous","cloned":false,"displayOrder":10,"editor-theme":"tunepad-dark","gain":0.39882110457021985,"hasError":false,"midi-input":false,"midi-output":false,"minimized":false,"pan":0,"patchId":367,"python":"playNote([48,52,55],beats=4)\nplayNote([53,57,60],beats=4)\nplayNote([55,59,62],beats=4)\nplayNote([48,52,55],beats=4)","show-editor":true,"show-instrument":true,"show-notation":true,"show-output":false,"show-timeline":true},"instrument":"bass","modified":"2025-11-07 09:33:34.554000","name":"Bass","public":false,"remix_parent":null,"version":"2.0","voice":"piano"},{"beats":8,"color":"#2f9aef","created":"2025-11-05 23:43:45.238000","deleted":false,"description":"","id":875701,"idata":{"author":"Anonymous","cloned":false,"displayOrder":11,"editor-theme":"tunepad-dark","gain":0.6659123909666057,"hasError":false,"midi-input":false,"midi-output":false,"minimized":false,"pan":0.0032812499999996803,"patchId":9,"python":"rest (2.00) \nplayNote(48, beats = 0.25)\nrest(0.25)\nplayNote(48, beats = 0.25)\nrest(0.25)\nplayNote(48, beats = 0.25)\nrest (2.75) \nplayNote(48, beats = 0.25)\nrest(0.25)\nplayNote(48, beats = 0.25)\nrest(0.25)\nplayNote(48, beats = 0.25)","show-editor":true,"show-instrument":true,"show-notation":true,"show-output":false,"show-timeline":true},"instrument":"piano","modified":"2025-11-07 09:54:27.360000","name":"Beat","public":false,"remix_parent":null,"version":"2.0","voice":"piano"},{"beats":4,"color":"#2f9aef","created":"2025-11-05 23:51:04.059000","deleted":false,"description":"","id":875702,"idata":{"author":"Anonymous","cloned":false,"displayOrder":12,"editor-theme":"tunepad-dark","gain":0.9468576780937307,"hasError":false,"midi-input":false,"midi-output":false,"minimized":false,"pan":0.8656250000000001,"patchId":9,"python":"playNote(48, beats = 1.00, sustain = 1)\nplayNote(50, beats = 0.25, sustain = 0.25)\nplayNote(53, beats = 0.25, sustain = 0.25)\nplayNote(57, beats = 0.25, sustain = 0.25)\nplayNote(59, beats = 0.25, sustain = 0.25)\nplayNote(60, beats = 1.00)       ","show-editor":true,"show-instrument":true,"show-notation":true,"show-output":false,"show-timeline":true},"instrument":"piano","modified":"2025-11-07 09:54:58.947000","name":"Scale","public":false,"remix_parent":null,"version":"2.0","voice":"piano"}],"id":113123,"import_export_version":1,"meter":"4/4","modified":"2025-11-07 09:23:54.290000","name":"Working with Data and Code A2","preview":null,"pucks":{"daw-zoom-factor":0.5,"key":"C major","owner_id":"7a88197d-a135-424e-895b-6d94347cbf2e"},"remix_parent":null,"summary":"","tags":[],"tracks":[{"clips":[{"beats":36,"color":"green","end":80,"start":0,"trim":0,"waveform":false}],"color":"green","gadget_id":859097,"gain":6.423648999501437,"hidden":false,"id":859097,"mute":false,"name":"Drum (Kick Drum Line)","order":0,"pan":0,"solo":false,"solo-mute":false},{"clips":[{"beats":8,"color":"green","end":80,"start":0,"trim":0,"waveform":false}],"color":"green","gadget_id":859106,"gain":4.336127144180389,"hidden":false,"id":859106,"mute":false,"name":"New Drums","order":1,"pan":0,"solo":false,"solo-mute":false},{"clips":[{"beats":8,"color":"green","end":80,"start":0,"trim":0,"waveform":false}],"color":"green","gadget_id":865963,"gain":4.472777259575499,"hidden":false,"id":865963,"mute":false,"name":"Snare","order":2,"pan":0,"solo":false,"solo-mute":false},{"clips":[{"beats":16,"color":"blue","end":80,"start":0,"trim":0,"waveform":false}],"color":"magenta","gadget_id":875565,"gain":0.25614961778840817,"hidden":false,"id":875565,"mute":false,"name":"New Keyboard","order":3,"pan":0,"solo":false,"solo-mute":false},{"clips":[{"beats":16,"color":"blue","end":80,"start":0,"trim":0,"waveform":false}],"color":"blue","gadget_id":875567,"gain":-1.0403074200108713,"hidden":false,"id":875567,"mute":false,"name":"New Keyboard 1","order":4,"pan":0,"solo":false,"solo-mute":false},{"clips":[{"beats":16,"color":"orange","end":80,"start":0,"trim":0,"waveform":false}],"color":"orange","gadget_id":875697,"gain":1.1852695320552407,"hidden":false,"id":875697,"mute":false,"name":"New Guitar 1","order":5,"pan":-0.6709375,"solo":false,"solo-mute":false},{"clips":[{"beats":16,"color":"orange","end":80,"start":0,"trim":0,"waveform":false}],"color":"orange","gadget_id":875698,"gain":0.6920199773531702,"hidden":false,"id":875698,"mute":false,"name":"New Guitar 1","order":6,"pan":0.2642187499999995,"solo":false,"solo-mute":false},{"clips":[{"beats":16,"color":"blue","end":80,"start":0,"trim":0,"waveform":false}],"color":"blue","gadget_id":875699,"gain":0.5147788310273621,"hidden":false,"id":875699,"mute":false,"name":"New Keyboard 1","order":7,"pan":0,"solo":false,"solo-mute":false},{"clips":[{"beats":16,"color":"magenta","end":80,"start":0,"trim":0,"waveform":false}],"color":"magenta","gadget_id":875700,"gain":0.7707260424140474,"hidden":false,"id":875700,"mute":false,"name":"New Bass","order":8,"pan":0,"solo":false,"solo-mute":false},{"clips":[{"beats":8,"color":"blue","end":80,"start":0,"trim":0,"waveform":false}],"color":"blue","gadget_id":875701,"gain":-3.531658077930592,"hidden":false,"id":875701,"mute":false,"name":"New Keyboard 1","order":9,"pan":0.0032812499999996803,"solo":false,"solo-mute":false},{"clips":[{"beats":4,"color":"blue","end":80,"start":0,"trim":0,"waveform":false}],"color":"blue","gadget_id":875702,"gain":-0.4743058954066967,"hidden":false,"id":875702,"mute":false,"name":"New Keyboard 1","order":10,"pan":0.8656250000000001,"solo":false,"solo-mute":false}],"user_id":"7a88197d-a135-424e-895b-6d94347cbf2e","username":"elina.mckay@student.uts.edu.au","visibility":"private"}